json_hints/__init__.py
json_hints/encoder.py
json_type_hints-1.3.dist-info/METADATA
json_type_hints-1.3.dist-info/WHEEL
json_type_hints-1.3.dist-info/licenses/LICENSE
json_type_hints-1.3.dist-info/RECORD
