Metadata-Version: 2.3
Name: json-type-hints
Version: 1.3
Summary: An extension of the standard json library
Project-URL: Homepage, https://github.com/cujoai/json-type-hints
Author-email: Darius Sirvidas <darius.sirvidas@cujo.com>
License-File: LICENSE
Classifier: License :: OSI Approved :: MIT License
Classifier: Operating System :: OS Independent
Classifier: Programming Language :: Python
Classifier: Programming Language :: Python :: 3
Classifier: Programming Language :: Python :: 3.10
Classifier: Programming Language :: Python :: 3.11
Classifier: Programming Language :: Python :: 3.12
Requires-Python: >=3.10
